labelearthengine_api-0.0.1.dist-info/licenses/LICENSE
le/__init__.py
le/_arg_types.py
le/_cloud_api_utils.py
le/_helpers.py
le/_utils.py
le/apifunction.py
le/apitestcase.py
le/batch.py
le/blob.py
le/classifier.py
le/clusterer.py
le/collection.py
le/computedobject.py
le/confusionmatrix.py
le/customfunction.py
le/data.py
le/daterange.py
le/deprecation.py
le/deserializer.py
le/dictionary.py
le/ee_array.py
le/ee_date.py
le/ee_exception.py
le/ee_list.py
le/ee_number.py
le/ee_string.py
le/ee_types.py
le/element.py
le/encodable.py
le/errormargin.py
le/feature.py
le/featurecollection.py
le/filter.py
le/function.py
le/geometry.py
le/image.py
le/image_converter.py
le/imagecollection.py
le/join.py
le/kernel.py
le/mapclient.py
le/model.py
le/oauth.py
le/pixeltype.py
le/projection.py
le/py.typed
le/reducer.py
le/rest_call.py
le/serializer.py
le/table_converter.py
le/terrain.py
le/cli/__init__.py
le/cli/commands.py
le/cli/eecli.py
le/cli/eecli_wrapper.py
le/cli/utils.py
le/tests/_cloud_api_utils_test.py
le/tests/_helpers_test.py
le/tests/_utils_test.py
le/tests/algorithms.json
le/tests/apifunction_test.py
le/tests/batch_test.py
le/tests/blob_test.py
le/tests/classifier_test.py
le/tests/cloud_api_discovery_document.json
le/tests/clusterer_test.py
le/tests/collection_test.py
le/tests/computedobject_test.py
le/tests/confusionmatrix_test.py
le/tests/data_test.py
le/tests/daterange_test.py
le/tests/deprecation_test.py
le/tests/deserializer_test.py
le/tests/dictionary_test.py
le/tests/ee_array_test.py
le/tests/ee_date_test.py
le/tests/ee_list_test.py
le/tests/ee_number_test.py
le/tests/ee_string_test.py
le/tests/ee_test.py
le/tests/ee_types_test.py
le/tests/element_test.py
le/tests/errormargin_test.py
le/tests/feature_test.py
le/tests/featurecollection_test.py
le/tests/filter_test.py
le/tests/function_test.py
le/tests/geometry_point_test.py
le/tests/geometry_test.py
le/tests/image_converter_test.py
le/tests/image_test.py
le/tests/imagecollection_test.py
le/tests/join_test.py
le/tests/kernel_test.py
le/tests/model_test.py
labelearthengine_api-0.0.1.dist-info/METADATA
labelearthengine_api-0.0.1.dist-info/WHEEL
labelearthengine_api-0.0.1.dist-info/entry_points.txt
labelearthengine_api-0.0.1.dist-info/top_level.txt
labelearthengine_api-0.0.1.dist-info/RECORD
